{
  "severity": "medium",
  "rule": "$.resource[*].aws_s3_bucket exists and ($.resource[*].aws_s3_bucket[*].*[*].logging anyNull)",
  "id": "41215510-c504-4752-ab38-0a36e49d55f8",
  "enabled": true,
  "resourceType": "s3",
  "policy": "AWS S3 CloudTrail buckets for which access logging is disabled",
  "description": "This policy identifies S3 CloudTrail buckets for which access is disabled.S3 Bucket access logging generates access records for each request made to your S3 bucket. An access log record contains information such as the request type, the resources specified in the request worked, and the time and date the request was processed. It is recommended that bucket access logging be enabled on the CloudTrail S3 bucket"
}
